{
    "Categories": 
        [
            {
                "name": "Mahabharatham Quotes"
            }
        ],
    
	"Wallpapers":
        [
			{
				"author": "Mahabharatham Quotes",
				"url": "https://mahabharathamquotes.files.wordpress.com/2018/01/mahabharatham-quotes-1.jpg?w=700&h=",
				"thumbUrl": "https://mahabharathamquotes.files.wordpress.com/2018/01/mahabharatham-quotes-1.jpg?w=150",
				"name": "1",
                "category": "mahabharatham quotes"
			},
		{
				"author": "Mahabharatham Quotes",
				"url": "https://mahabharathamquotes.files.wordpress.com/2018/01/mahabharatham-quotes-2.jpg?w=700&h=",
				"thumbUrl": "https://mahabharathamquotes.files.wordpress.com/2018/01/mahabharatham-quotes-2.jpg?w=150",
				"name": "2",
                "category": "mahabharatham quotes"
			},
		{
				"author": "Mahabharatham Quotes",
				"url": "https://mahabharathamquotes.files.wordpress.com/2018/01/mahabharatham-quotes-3.jpg?w=700&h=",
				"thumbUrl": "https://mahabharathamquotes.files.wordpress.com/2018/01/mahabharatham-quotes-3.jpg?w=150",
				"name": "3",
                "category": "mahabharatham quotes"
			},
		{
				"author": "Mahabharatham Quotes",
				"url": "https://mahabharathamquotes.files.wordpress.com/2018/01/mahabharatham-quotes-4.jpg",
				"thumbUrl": "https://mahabharathamquotes.files.wordpress.com/2018/01/mahabharatham-quotes-4.jpg?w=150",
				"name": "4",
                "category": "mahabharatham quotes"
			},
		{
				"author": "Mahabharatham Quotes",
				"url": "https://mahabharathamquotes.files.wordpress.com/2018/01/mahabharatham-quotes-5.jpg?w=700&h=",
				"thumbUrl": "https://mahabharathamquotes.files.wordpress.com/2018/01/mahabharatham-quotes-5.jpg?w=150",
				"name": "5",
                "category": "mahabharatham quotes"
			},
		{
				"author": "Mahabharatham Quotes",
				"url": "https://mahabharathamquotes.files.wordpress.com/2018/01/mahabharatham-quotes-6.jpg?w=700&h=",
				"thumbUrl": "https://mahabharathamquotes.files.wordpress.com/2018/01/mahabharatham-quotes-6.jpg?w=150",
				"name": "6",
                "category": "mahabharatham quotes"
			},
		{
				"author": "Mahabharatham Quotes",
				"url": "https://mahabharathamquotes.files.wordpress.com/2018/01/mahabharatham-quotes-7.jpg?w=700&h=",
				"thumbUrl": "https://mahabharathamquotes.files.wordpress.com/2018/01/mahabharatham-quotes-7.jpg?w=150",
				"name": "7",
                "category": "mahabharatham quotes"
			},
		{
				"author": "Mahabharatham Quotes",
				"url": "https://mahabharathamquotes.files.wordpress.com/2018/01/mahabharatham-quotes-8.jpg?w=700&h=",
				"thumbUrl": "https://mahabharathamquotes.files.wordpress.com/2018/01/mahabharatham-quotes-8.jpg?w=150",
				"name": "8",
                "category": "mahabharatham quotes"
			},
		{
				"author": "Mahabharatham Quotes",
				"url": "https://mahabharathamquotes.files.wordpress.com/2018/01/mahabharatham-quotes-9.jpg?w=700&h=",
				"thumbUrl": "https://mahabharathamquotes.files.wordpress.com/2018/01/mahabharatham-quotes-9.jpg?w=150",
				"name": "9",
                "category": "mahabharatham quotes"
			},
		{
				"author": "Mahabharatham Quotes",
				"url": "https://mahabharathamquotes.files.wordpress.com/2018/01/mahabharatham-quotes-10.jpg?w=700&h=",
				"thumbUrl": "https://mahabharathamquotes.files.wordpress.com/2018/01/mahabharatham-quotes-10.jpg?w=150",
				"name": "10",
                "category": "mahabharatham quotes"
			},
		{
				"author": "Mahabharatham Quotes",
				"url": "https://mahabharathamquotes.files.wordpress.com/2018/01/mahabharatham-quotes-11.jpg?w=700&h=",
				"thumbUrl": "https://mahabharathamquotes.files.wordpress.com/2018/01/mahabharatham-quotes-11.jpg?w=150",
				"name": "11",
                "category": "mahabharatham quotes"
			},
		{
				"author": "Mahabharatham Quotes",
				"url": "https://mahabharathamquotes.files.wordpress.com/2018/01/mahabharatham-quotes-12.jpg?w=700&h=",
				"thumbUrl": "https://mahabharathamquotes.files.wordpress.com/2018/01/mahabharatham-quotes-12.jpg?w=150",
				"name": "12",
                "category": "mahabharatham quotes"
			},
		{
				"author": "Mahabharatham Quotes",
				"url": "https://mahabharathamquotes.files.wordpress.com/2018/01/mahabharatham-quotes-13.jpg?w=700&h=",
				"thumbUrl": "https://mahabharathamquotes.files.wordpress.com/2018/01/mahabharatham-quotes-13.jpg?w=150",
				"name": "13",
                "category": "mahabharatham quotes"
			},
		{
				"author": "Mahabharatham Quotes",
				"url": "https://mahabharathamquotes.files.wordpress.com/2018/01/mahabharatham-quotes-14.jpg?w=700&h=",
				"thumbUrl": "https://mahabharathamquotes.files.wordpress.com/2018/01/mahabharatham-quotes-14.jpg?w=150",
				"name": "14",
                "category": "mahabharatham quotes"
			},
		{
				"author": "Mahabharatham Quotes",
				"url": "https://mahabharathamquotes.files.wordpress.com/2018/01/mahabharatham-quotes-15.jpg?w=700&h=",
				"thumbUrl": "https://mahabharathamquotes.files.wordpress.com/2018/01/mahabharatham-quotes-15.jpg?w=150",
				"name": "15",
                "category": "mahabharatham quotes"
			},
		{
				"author": "Mahabharatham Quotes",
				"url": "https://mahabharathamquotes.files.wordpress.com/2018/01/mahabharatham-quotes-16.jpg?w=700&h=",
				"thumbUrl": "https://mahabharathamquotes.files.wordpress.com/2018/01/mahabharatham-quotes-16.jpg?w=150",
				"name": "16",
                "category": "mahabharatham quotes"
			},
		{
				"author": "Mahabharatham Quotes",
				"url": "https://mahabharathamquotes.files.wordpress.com/2018/01/mahabharatham-quotes-17.jpg?w=700&h=",
				"thumbUrl": "https://mahabharathamquotes.files.wordpress.com/2018/01/mahabharatham-quotes-17.jpg?w=150",
				"name": "17",
                "category": "mahabharatham quotes"
			},
		{
				"author": "Mahabharatham Quotes",
				"url": "https://mahabharathamquotes.files.wordpress.com/2018/01/mahabharatham-quotes-18.jpg?w=700&h=",
				"thumbUrl": "https://mahabharathamquotes.files.wordpress.com/2018/01/mahabharatham-quotes-18.jpg?w=150",
				"name": "18",
                "category": "mahabharatham quotes"
			},
		{
				"author": "Mahabharatham Quotes",
				"url": "https://mahabharathamquotes.files.wordpress.com/2018/01/mahabharatham-quotes-19.jpg?w=700&h=",
				"thumbUrl": "https://mahabharathamquotes.files.wordpress.com/2018/01/mahabharatham-quotes-19.jpg?w=150",
				"name": "19",
                "category": "mahabharatham quotes"
			},
		{
				"author": "Mahabharatham Quotes",
				"url": "https://mahabharathamquotes.files.wordpress.com/2018/01/mahabharatham-quotes-20.jpg?w=700&h=",
				"thumbUrl": "https://mahabharathamquotes.files.wordpress.com/2018/01/mahabharatham-quotes-20.jpg?w=150",
				"name": "20",
                "category": "mahabharatham quotes"
			},
		{
				"author": "Mahabharatham Quotes",
				"url": "https://mahabharathamquotes.files.wordpress.com/2018/01/mahabharatham-quotes-21.jpg?w=700&h=",
				"thumbUrl": "https://mahabharathamquotes.files.wordpress.com/2018/01/mahabharatham-quotes-21.jpg?w=150",
				"name": "21",
                "category": "mahabharatham quotes"
			},
		{
				"author": "Mahabharatham Quotes",
				"url": "https://mahabharathamquotes.files.wordpress.com/2018/01/mahabharatham-quotes-22.jpg?w=700&h=",
				"thumbUrl": "https://mahabharathamquotes.files.wordpress.com/2018/01/mahabharatham-quotes-22.jpg?w=150",
				"name": "22",
                "category": "mahabharatham quotes"
			},
		{
				"author": "Mahabharatham Quotes",
				"url": "https://mahabharathamquotes.files.wordpress.com/2018/01/mahabharatham-quotes-23.jpg?w=700&h=",
				"thumbUrl": "https://mahabharathamquotes.files.wordpress.com/2018/01/mahabharatham-quotes-23.jpg?w=150",
				"name": "23",
                "category": "mahabharatham quotes"
			},
		{
				"author": "Mahabharatham Quotes",
				"url": "https://mahabharathamquotes.files.wordpress.com/2018/01/mahabharatham-quotes-24.jpg?w=700&h=",
				"thumbUrl": "https://mahabharathamquotes.files.wordpress.com/2018/01/mahabharatham-quotes-24.jpg?w=150",
				"name": "24",
                "category": "mahabharatham quotes"
			},{
				"author": "Mahabharatham Quotes",
				"url": "https://mahabharathamquotes.files.wordpress.com/2018/01/mahabharatham-quotes-25.jpg?w=700&h=",
				"thumbUrl": "https://mahabharathamquotes.files.wordpress.com/2018/01/mahabharatham-quotes-25.jpg?w=150",
				"name": "25",
                "category": "mahabharatham quotes"
			},
		{
				"author": "Mahabharatham Quotes",
				"url": "https://mahabharathamquotes.files.wordpress.com/2018/01/mahabharatham-quotes-26.jpg?w=700&h=",
				"thumbUrl": "https://mahabharathamquotes.files.wordpress.com/2018/01/mahabharatham-quotes-26.jpg?w=150",
				"name": "26",
                "category": "mahabharatham quotes"
			},
		{
				"author": "Mahabharatham Quotes",
				"url": "https://mahabharathamquotes.files.wordpress.com/2018/01/mahabharatham-quotes-27.jpg?w=700&h=",
				"thumbUrl": "https://mahabharathamquotes.files.wordpress.com/2018/01/mahabharatham-quotes-27.jpg?w=150",
				"name": "27",
                "category": "mahabharatham quotes"
			},
		{
				"author": "Mahabharatham Quotes",
				"url": "https://mahabharathamquotes.files.wordpress.com/2018/01/mahabharatham-quotes-28.jpg?w=700&h=",
				"thumbUrl": "https://mahabharathamquotes.files.wordpress.com/2018/01/mahabharatham-quotes-28.jpg?w=150",
				"name": "28",
                "category": "mahabharatham quotes"
			},
		{
				"author": "Mahabharatham Quotes",
				"url": "https://mahabharathamquotes.files.wordpress.com/2018/01/mahabharatham-quotes-29.jpg?w=700&h=",
				"thumbUrl": "https://mahabharathamquotes.files.wordpress.com/2018/01/mahabharatham-quotes-29.jpg?w=150",
				"name": "29",
                "category": "mahabharatham quotes"
			},
		{
				"author": "Mahabharatham Quotes",
				"url": "https://mahabharathamquotes.files.wordpress.com/2018/01/mahabharatham-quotes-30.jpg?w=700&h=",
				"thumbUrl": "https://mahabharathamquotes.files.wordpress.com/2018/01/mahabharatham-quotes-30.jpg?w=150",
				"name": "30",
                "category": "mahabharatham quotes"
			},
		{
				"author": "Mahabharatham Quotes",
				"url": "https://mahabharathamquotes.files.wordpress.com/2018/01/mahabharatham-quotes-31.jpg?w=700&h=",
				"thumbUrl": "https://mahabharathamquotes.files.wordpress.com/2018/01/mahabharatham-quotes-31.jpg?w=150",
				"name": "31",
                "category": "mahabharatham quotes"
			},
		{
				"author": "Mahabharatham Quotes",
				"url": "https://mahabharathamquotes.files.wordpress.com/2018/01/mahabharatham-quotes-32.jpg?w=700&h=",
				"thumbUrl": "https://mahabharathamquotes.files.wordpress.com/2018/01/mahabharatham-quotes-32.jpg?w=150",
				"name": "32",
                "category": "mahabharatham quotes"
			},
		{
				"author": "Mahabharatham Quotes",
				"url": "https://mahabharathamquotes.files.wordpress.com/2018/01/mahabharatham-quotes-33.jpg?w=700&h=",
				"thumbUrl": "https://mahabharathamquotes.files.wordpress.com/2018/01/mahabharatham-quotes-33.jpg?w=150",
				"name": "33",
                "category": "mahabharatham quotes"
			},
		{
				"author": "Mahabharatham Quotes",
				"url": "https://mahabharathamquotes.files.wordpress.com/2018/01/mahabharatham-quotes-34.jpg?w=700&h=",
				"thumbUrl": "https://mahabharathamquotes.files.wordpress.com/2018/01/mahabharatham-quotes-34.jpg?w=150",
				"name": "34",
                "category": "mahabharatham quotes"
			},
		{
				"author": "Mahabharatham Quotes",
				"url": "https://mahabharathamquotes.files.wordpress.com/2018/01/mahabharatham-quotes-35.jpg?w=700&h=",
				"thumbUrl": "https://mahabharathamquotes.files.wordpress.com/2018/01/mahabharatham-quotes-35.jpg?w=150",
				"name": "35",
                "category": "mahabharatham quotes"
			},
		{
				"author": "Mahabharatham Quotes",
				"url": "https://mahabharathamquotes.files.wordpress.com/2018/01/mahabharatham-quotes-36.jpg?w=700&h=",
				"thumbUrl": "https://mahabharathamquotes.files.wordpress.com/2018/01/mahabharatham-quotes-36.jpg?w=150",
				"name": "36",
                "category": "mahabharatham quotes"
			},
		{
				"author": "Mahabharatham Quotes",
				"url": "https://mahabharathamquotes.files.wordpress.com/2018/01/mahabharatham-quotes-37.jpg?w=700&h=",
				"thumbUrl": "https://mahabharathamquotes.files.wordpress.com/2018/01/mahabharatham-quotes-37.jpg?w=150",
				"name": "37",
                "category": "mahabharatham quotes"
			},
		{
				"author": "Mahabharatham Quotes",
				"url": "https://mahabharathamquotes.files.wordpress.com/2018/01/mahabharatham-quotes-38.jpg?w=700&h=",
				"thumbUrl": "https://mahabharathamquotes.files.wordpress.com/2018/01/mahabharatham-quotes-38.jpg?w=150",
				"name": "38",
                "category": "mahabharatham quotes"
			},
		{
				"author": "Mahabharatham Quotes",
				"url": "https://mahabharathamquotes.files.wordpress.com/2018/01/mahabharatham-quotes-39.jpg?w=1000&h=",
				"thumbUrl": "https://mahabharathamquotes.files.wordpress.com/2018/01/mahabharatham-quotes-39.jpg?w=150",
				"name": "39",
                "category": "mahabharatham quotes"
			},
		{
				"author": "Mahabharatham Quotes",
				"url": "https://mahabharathamquotes.files.wordpress.com/2018/01/mahabharatham-quotes-40.jpg?w=700&h=",
				"thumbUrl": "https://mahabharathamquotes.files.wordpress.com/2018/01/mahabharatham-quotes-40.jpg?w=150",
				"name": "40",
                "category": "mahabharatham quotes"
			},
		{
				"author": "Mahabharatham Quotes",
				"url": "https://mahabharathamquotes.files.wordpress.com/2018/01/mahabharatham-quotes-41.jpg?w=700&h=",
				"thumbUrl": "https://mahabharathamquotes.files.wordpress.com/2018/01/mahabharatham-quotes-41.jpg?w=150",
				"name": "41",
                "category": "mahabharatham quotes"
			},
		{
				"author": "Mahabharatham Quotes",
				"url": "https://mahabharathamquotes.files.wordpress.com/2018/01/mahabharatham-quotes-42.jpg?w=700&h=",
				"thumbUrl": "https://mahabharathamquotes.files.wordpress.com/2018/01/mahabharatham-quotes-42.jpg?w=150",
				"name": "42",
                "category": "mahabharatham quotes"
			},
		{
				"author": "Mahabharatham Quotes",
				"url": "https://mahabharathamquotes.files.wordpress.com/2018/01/mahabharatham-quotes-43.jpg?w=700&h=",
				"thumbUrl": "https://mahabharathamquotes.files.wordpress.com/2018/01/mahabharatham-quotes-43.jpg?w=150",
				"name": "43",
                "category": "mahabharatham quotes"
			},
		{
				"author": "Mahabharatham Quotes",
				"url": "https://mahabharathamquotes.files.wordpress.com/2018/01/mahabharatham-quotes-44.jpg?w=700&h=",
				"thumbUrl": "https://mahabharathamquotes.files.wordpress.com/2018/01/mahabharatham-quotes-44.jpg?w=150",
				"name": "44",
                "category": "mahabharatham quotes"
			},
		{
				"author": "Mahabharatham Quotes",
				"url": "https://mahabharathamquotes.files.wordpress.com/2018/01/mahabharatham-quotes-45.jpg?w=700&h=",
				"thumbUrl": "https://mahabharathamquotes.files.wordpress.com/2018/01/mahabharatham-quotes-45.jpg?w=150",
				"name": "45",
                "category": "mahabharatham quotes"
			},
		{
				"author": "Mahabharatham Quotes",
				"url": "https://mahabharathamquotes.files.wordpress.com/2018/01/mahabharatham-quotes-46.jpg?w=700&h=",
				"thumbUrl": "https://mahabharathamquotes.files.wordpress.com/2018/01/mahabharatham-quotes-46.jpg?w=150",
				"name": "46",
                "category": "mahabharatham quotes"
			},
		{
				"author": "Mahabharatham Quotes",
				"url": "https://mahabharathamquotes.files.wordpress.com/2018/01/mahabharatham-quotes-47.jpg?w=700&h=",
				"thumbUrl": "https://mahabharathamquotes.files.wordpress.com/2018/01/mahabharatham-quotes-47.jpg?w=150",
				"name": "47",
                "category": "mahabharatham quotes"
			},
		{
				"author": "Mahabharatham Quotes",
				"url": "https://mahabharathamquotes.files.wordpress.com/2018/01/mahabharatham-quotes-48.jpg?w=700&h=",
				"thumbUrl": "https://mahabharathamquotes.files.wordpress.com/2018/01/mahabharatham-quotes-48.jpg?w=150",
				"name": "48",
                "category": "mahabharatham quotes"
			},
		{
				"author": "Mahabharatham Quotes",
				"url": "https://mahabharathamquotes.files.wordpress.com/2018/01/mahabharatham-quotes-49.jpg?w=370&h=",
				"thumbUrl": "https://mahabharathamquotes.files.wordpress.com/2018/01/mahabharatham-quotes-49.jpg?w=101",
				"name": "49",
                "category": "mahabharatham quotes"
			},
		{
				"author": "Mahabharatham Quotes",
				"url": "https://mahabharathamquotes.files.wordpress.com/2018/01/mahabharatham-quotes-50.jpg?w=700&h=",
				"thumbUrl": "https://mahabharathamquotes.files.wordpress.com/2018/01/mahabharatham-quotes-50.jpg?w=150",
				"name": "50",
                "category": "mahabharatham quotes"
			},
		{
				"author": "Mahabharatham Quotes",
				"url": "https://mahabharathamquotes.files.wordpress.com/2018/01/mahabharatham-quotes-50.jpg?w=700&h=",
				"thumbUrl": "https://mahabharathamquotes.files.wordpress.com/2018/01/mahabharatham-quotes-51.jpg?w=150",
				"name": "51",
                "category": "mahabharatham quotes"
			},
		{
				"author": "Mahabharatham Quotes",
				"url": "https://mahabharathamquotes.files.wordpress.com/2018/01/mahabharatham-quotes-52.jpg?w=700&h=",
				"thumbUrl": "https://mahabharathamquotes.files.wordpress.com/2018/01/mahabharatham-quotes-52.jpg?w=150",
				"name": "52",
                "category": "mahabharatham quotes"
			},
		{
				"author": "Mahabharatham Quotes",
				"url": "",
				"thumbUrl": "",
				"name": "53",
                "category": "mahabharatham quotes"
			},
		{
				"author": "Mahabharatham Quotes",
				"url": "",
				"thumbUrl": "",
				"name": "54",
                "category": "mahabharatham quotes"
			},
		{
				"author": "Mahabharatham Quotes",
				"url": "",
				"thumbUrl": "",
				"name": "55",
                "category": "mahabharatham quotes"
			},
		{
				"author": "Mahabharatham Quotes",
				"url": "",
				"thumbUrl": "",
				"name": "56",
                "category": "mahabharatham quotes"
			},
		{
				"author": "Mahabharatham Quotes",
				"url": "",
				"thumbUrl": "",
				"name": "57",
                "category": "mahabharatham quotes"
			},
		{
				"author": "Mahabharatham Quotes",
				"url": "",
				"thumbUrl": "",
				"name": "58",
                "category": "mahabharatham quotes"
			},
		{
				"author": "Mahabharatham Quotes",
				"url": "",
				"thumbUrl": "",
				"name": "59",
                "category": "mahabharatham quotes"
			},
		{
				"author": "Mahabharatham Quotes",
				"url": "",
				"thumbUrl": "",
				"name": "60",
                "category": "mahabharatham quotes"
			},
		{
				"author": "Mahabharatham Quotes",
				"url": "",
				"thumbUrl": "",
				"name": "61",
                "category": "mahabharatham quotes"
			},
		{
				"author": "Mahabharatham Quotes",
				"url": "",
				"thumbUrl": "",
				"name": "62",
                "category": "mahabharatham quotes"
			},
		{
				"author": "Mahabharatham Quotes",
				"url": "",
				"thumbUrl": "",
				"name": "63",
                "category": "mahabharatham quotes"
			},
		{
				"author": "Mahabharatham Quotes",
				"url": "",
				"thumbUrl": "",
				"name": "64",
                "category": "mahabharatham quotes"
			},
		{
				"author": "Mahabharatham Quotes",
				"url": "",
				"thumbUrl": "",
				"name": "65",
                "category": "mahabharatham quotes"
			},
		{
				"author": "Mahabharatham Quotes",
				"url": "",
				"thumbUrl": "",
				"name": "66",
                "category": "mahabharatham quotes"
			},
		{
				"author": "Mahabharatham Quotes",
				"url": "",
				"thumbUrl": "",
				"name": "67",
                "category": "mahabharatham quotes"
			},
		{
				"author": "Mahabharatham Quotes",
				"url": "",
				"thumbUrl": "",
				"name": "68",
                "category": "mahabharatham quotes"
			},
		{
				"author": "Mahabharatham Quotes",
				"url": "",
				"thumbUrl": "",
				"name": "69",
                "category": "mahabharatham quotes"
			},
		{
				"author": "Mahabharatham Quotes",
				"url": "",
				"thumbUrl": "",
				"name": "70",
                "category": "mahabharatham quotes"
			},
		{
				"author": "Mahabharatham Quotes",
				"url": "",
				"thumbUrl": "",
				"name": "71",
                "category": "mahabharatham quotes"
			},
		{
				"author": "Mahabharatham Quotes",
				"url": "",
				"thumbUrl": "",
				"name": "72",
                "category": "mahabharatham quotes"
			},
		{
				"author": "Mahabharatham Quotes",
				"url": "",
				"thumbUrl": "",
				"name": "73",
                "category": "mahabharatham quotes"
			},
		{
				"author": "Mahabharatham Quotes",
				"url": "",
				"thumbUrl": "",
				"name": "74",
                "category": "mahabharatham quotes"
			},
		{
				"author": "Mahabharatham Quotes",
				"url": "",
				"thumbUrl": "",
				"name": "75",
                "category": "mahabharatham quotes"
			},
		{
				"author": "Mahabharatham Quotes",
				"url": "",
				"thumbUrl": "",
				"name": "76",
                "category": "mahabharatham quotes"
			},
		{
				"author": "Mahabharatham Quotes",
				"url": "",
				"thumbUrl": "",
				"name": "77",
                "category": "mahabharatham quotes"
			},
		
		{
				"author": "Mahabharatham Quotes",
				"url": "",
				"thumbUrl": "",
				"name": "78",
                "category": "mahabharatham quotes"
			},
		
		{
				"author": "Mahabharatham Quotes",
				"url": "",
				"thumbUrl": "",
				"name": "79",
                "category": "mahabharatham quotes"
			},
		
		{
				"author": "Mahabharatham Quotes",
				"url": "",
				"thumbUrl": "",
				"name": "80",
                "category": "mahabharatham quotes"
			},
		
		{
				"author": "Mahabharatham Quotes",
				"url": "",
				"thumbUrl": "",
				"name": "81",
                "category": "mahabharatham quotes"
			},
		
		{
				"author": "Mahabharatham Quotes",
				"url": "",
				"thumbUrl": "",
				"name": "82",
                "category": "mahabharatham quotes"
			},
		
		{
				"author": "Mahabharatham Quotes",
				"url": "",
				"thumbUrl": "",
				"name": "83",
                "category": "mahabharatham quotes"
			},
		
		{
				"author": "Mahabharatham Quotes",
				"url": "",
				"thumbUrl": "",
				"name": "84",
                "category": "mahabharatham quotes"
			},
		
		{
				"author": "Mahabharatham Quotes",
				"url": "",
				"thumbUrl": "",
				"name": "85",
                "category": "mahabharatham quotes"
			},
		
		{
				"author": "Mahabharatham Quotes",
				"url": "",
				"thumbUrl": "",
				"name": "86",
                "category": "mahabharatham quotes"
			},
		
		{
				"author": "Mahabharatham Quotes",
				"url": "",
				"thumbUrl": "",
				"name": "87",
                "category": "mahabharatham quotes"
			},
		
		{
				"author": "Mahabharatham Quotes",
				"url": "",
				"thumbUrl": "",
				"name": "88",
                "category": "mahabharatham quotes"
			},
		
		{
				"author": "Mahabharatham Quotes",
				"url": "",
				"thumbUrl": "",
				"name": "89",
                "category": "mahabharatham quotes"
			},
		
		{
				"author": "Mahabharatham Quotes",
				"url": "",
				"thumbUrl": "",
				"name": "90",
                "category": "mahabharatham quotes"
			},
		
		{
				"author": "Mahabharatham Quotes",
				"url": "",
				"thumbUrl": "",
				"name": "91",
                "category": "mahabharatham quotes"
			},
		
		{
				"author": "Mahabharatham Quotes",
				"url": "",
				"thumbUrl": "",
				"name": "92",
                "category": "mahabharatham quotes"
			},
		
		{
				"author": "Mahabharatham Quotes",
				"url": "",
				"thumbUrl": "",
				"name": "93",
                "category": "mahabharatham quotes"
			},
		
		{
				"author": "Mahabharatham Quotes",
				"url": "",
				"thumbUrl": "",
				"name": "94",
                "category": "mahabharatham quotes"
			},
		
		{
				"author": "Mahabharatham Quotes",
				"url": "",
				"thumbUrl": "",
				"name": "95",
                "category": "mahabharatham quotes"
			},
		
		{
				"author": "Mahabharatham Quotes",
				"url": "",
				"thumbUrl": "",
				"name": "96",
                "category": "mahabharatham quotes"
			},
		
		{
				"author": "Mahabharatham Quotes",
				"url": "",
				"thumbUrl": "",
				"name": "97",
                "category": "mahabharatham quotes"
			},
		
		{
				"author": "Mahabharatham Quotes",
				"url": "",
				"thumbUrl": "",
				"name": "98",
                "category": "mahabharatham quotes"
			},
		
		{
				"author": "Mahabharatham Quotes",
				"url": "",
				"thumbUrl": "",
				"name": "99",
                "category": "mahabharatham quotes"
			},
		
		{
				"author": "Mahabharatham Quotes",
				"url": "",
				"thumbUrl": "",
				"name": "100",
                "category": "mahabharatham quotes"
			},
		
		{
				"author": "Mahabharatham Quotes",
				"url": "",
				"thumbUrl": "",
				"name": "101",
                "category": "mahabharatham quotes"
			},
		
		{
				"author": "Mahabharatham Quotes",
				"url": "",
				"thumbUrl": "",
				"name": "102",
                "category": "mahabharatham quotes"
			},
		
		{
				"author": "Mahabharatham Quotes",
				"url": "",
				"thumbUrl": "",
				"name": "103",
                "category": "mahabharatham quotes"
			},
		
		{
				"author": "Mahabharatham Quotes",
				"url": "",
				"thumbUrl": "",
				"name": "104",
                "category": "mahabharatham quotes"
			},
		
		{
				"author": "Mahabharatham Quotes",
				"url": "",
				"thumbUrl": "",
				"name": "105",
                "category": "mahabharatham quotes"
			},
		
		{
				"author": "Mahabharatham Quotes",
				"url": "",
				"thumbUrl": "",
				"name": "106",
                "category": "mahabharatham quotes"
			},
		
		{
				"author": "Mahabharatham Quotes",
				"url": "",
				"thumbUrl": "",
				"name": "107",
                "category": "mahabharatham quotes"
			},
		
		{
				"author": "Mahabharatham Quotes",
				"url": "",
				"thumbUrl": "",
				"name": "108",
                "category": "mahabharatham quotes"
			},
		
		{
				"author": "Mahabharatham Quotes",
				"url": "",
				"thumbUrl": "",
				"name": "109",
                "category": "mahabharatham quotes"
			},
		
		{
				"author": "Mahabharatham Quotes",
				"url": "",
				"thumbUrl": "",
				"name": "110",
                "category": "mahabharatham quotes"
			},
		
		{
				"author": "Mahabharatham Quotes",
				"url": "",
				"thumbUrl": "",
				"name": "111",
                "category": "mahabharatham quotes"
			},
		
		{
				"author": "Mahabharatham Quotes",
				"url": "",
				"thumbUrl": "",
				"name": "112",
                "category": "mahabharatham quotes"
			},
		
		{
				"author": "Mahabharatham Quotes",
				"url": "",
				"thumbUrl": "",
				"name": "113",
                "category": "mahabharatham quotes"
			},
		
		{
				"author": "Mahabharatham Quotes",
				"url": "",
				"thumbUrl": "",
				"name": "114",
                "category": "mahabharatham quotes"
			},
		
		{
				"author": "Mahabharatham Quotes",
				"url": "",
				"thumbUrl": "",
				"name": "115",
                "category": "mahabharatham quotes"
			},
		
		{
				"author": "Mahabharatham Quotes",
				"url": "",
				"thumbUrl": "",
				"name": "116",
                "category": "mahabharatham quotes"
			},
		
		{
				"author": "Mahabharatham Quotes",
				"url": "",
				"thumbUrl": "",
				"name": "117",
                "category": "mahabharatham quotes"
			},
		
		{
				"author": "Mahabharatham Quotes",
				"url": "",
				"thumbUrl": "",
				"name": "118",
                "category": "mahabharatham quotes"
			},
		
		{
				"author": "Mahabharatham Quotes",
				"url": "",
				"thumbUrl": "",
				"name": "119",
                "category": "mahabharatham quotes"
			},
		
		{
				"author": "Mahabharatham Quotes",
				"url": "",
				"thumbUrl": "",
				"name": "120",
                "category": "mahabharatham quotes"
			},
		
		{
				"author": "Mahabharatham Quotes",
				"url": "",
				"thumbUrl": "",
				"name": "121",
                "category": "mahabharatham quotes"
			},
		
		{
				"author": "Mahabharatham Quotes",
				"url": "",
				"thumbUrl": "",
				"name": "122",
                "category": "mahabharatham quotes"
			}
		]
}
